datacleanser/__init__.py
datacleanser/core.py
datacleanser-0.1.0.dist-info/licenses/LICENSE
datacleanser-0.1.0.dist-info/METADATA
datacleanser-0.1.0.dist-info/WHEEL
datacleanser-0.1.0.dist-info/top_level.txt
datacleanser-0.1.0.dist-info/RECORD
