Metadata-Version: 2.4
Name: datacleanser
Version: 0.1.0
Summary: A utility to clean and normalize 2D data structures
Home-page: https://github.com/yourusername/datacleanser
Author: Balraj Sellamuthu
Author-email: balrajsellamuthu30@gmail.com
License: MIT
Classifier: Programming Language :: Python :: 3
Classifier: License :: OSI Approved :: MIT License
Classifier: Operating System :: OS Independent
Requires-Python: >=3.7
License-File: LICENSE
Requires-Dist: numpy
Requires-Dist: pandas
Dynamic: license-file
